<?xml version="1.0" encoding="utf-8"?>
<root xmlns:xsd="http://www.w3.org/2001/XMLSchema" xmlns:xsi="http://www.w3.org/2001/XMLSchema-instance">
  <metadata>
    <schemaversion>2.0</schemaversion>
    <version>0.9</version>
    <id>D096E1F1-D90A-4BC3-8A67-EFD252708FF6</id>
    <displayname>Disable 3rd Party Components (John Billekens)</displayname>
    <description>Disables 3rd party components (scheduled tasks and services) added by Adobe and Google (John Billekens)</description>
    <category>OS Optimizations</category>
    <author>John Billekens</author>
    <lastupdatedate>3/11/2020</lastupdatedate>
  </metadata>
  <group>
    <id>Adobe</id>
    <displayname>Adobe</displayname>
    <description>Configures Adobe items</description>
    <entry>
      <name>Adobe Acrobat Update Task</name>
      <description>This task keeps your Adobe Reader and Acrobat applications up to date with the latest enhancements and security fixes</description>
      <execute>1</execute>
      <action>
        <plugin>SchTasks</plugin>
        <params>
          <name>Adobe Acrobat Update Task</name>
          <path>\</path>
          <value>Disabled</value>
        </params>
      </action>
    </entry>
    <entry>
      <name>Adobe Acrobat Update Service (AdobeARMservice)</name>
      <description>Adobe Acrobat Updater keeps your Adobe software up to date.</description>
      <execute>1</execute>
      <action>
        <plugin>Services</plugin>
        <params>
          <name>AdobeARMservice</name>
          <value>Disabled</value>
        </params>
      </action>
    </entry>
    <entry>
      <name>Adobe Flash Player PPAPI Notifier Task</name>
      <description>This task keeps your Adobe Flash PPAPI Player installation up to date with the latest enhancements and security fixes. If this task is disabled or removed, Adobe Flash Player will be unable to automatically secure your machine with the latest security fixes.</description>
      <execute>1</execute>
      <action>
        <plugin>SchTasks</plugin>
        <params>
          <name>Adobe Flash Player PPAPI Notifier</name>
          <path>\</path>
          <value>Disabled</value>
        </params>
      </action>
    </entry>
    <entry>
      <name>Adobe Flash Player NPAPI Notifier Task</name>
      <description>This task keeps your Adobe Flash NPAPI Player installation up to date with the latest enhancements and security fixes. If this task is disabled or removed, Adobe Flash Player will be unable to automatically secure your machine with the latest security fixes.</description>
      <execute>1</execute>
      <action>
        <plugin>SchTasks</plugin>
        <params>
          <name>Adobe Flash Player NPAPI Notifier</name>
          <path>\</path>
          <value>Disabled</value>
        </params>
      </action>
    </entry>
    <entry>
      <name>Adobe Flash Player Updater Task</name>
      <description>This task keeps your Adobe Flash Player installation up to date with the latest enhancements and security fixes. If this task is disabled or removed, Adobe Flash Player will be unable to automatically secure your machine with the latest security fixes.</description>
      <execute>1</execute>
      <action>
        <plugin>SchTasks</plugin>
        <params>
          <name>Adobe Flash Player Updater</name>
          <path>\</path>
          <value>Disabled</value>
        </params>
      </action>
    </entry>
    <entry>
      <name>Adobe Flash Player Updater Service (AdobeFlashPlayerUpdateSvc)</name>
      <description>This service keeps your Adobe Flash Player installation up to date with the latest enhancements</description>
      <execute>1</execute>
      <action>
        <plugin>Services</plugin>
        <params>
          <name>AdobeFlashPlayerUpdateSvc</name>
          <value>Disabled</value>
        </params>
      </action>
    </entry>
    <entry>
      <name>Adobe Genuine Monitor Service (AGMService)</name>
      <description>Adobe Genuine Monitor Service</description>
      <execute>1</execute>
      <action>
        <plugin>Services</plugin>
        <params>
          <name>AGMService</name>
          <value>Disabled</value>
        </params>
      </action>
    </entry>
    <entry>
      <name>Adobe Genuine Software Integrity Service (AGSService)</name>
      <description>Adobe Genuine Software Integrity Service</description>
      <execute>1</execute>
      <action>
        <plugin>Services</plugin>
        <params>
          <name>AGSService</name>
          <value>Disabled</value>
        </params>
      </action>
    </entry>
    <entry>
      <name>Creative Cloud desktop app Update Service (AdobeUpdateService)</name>
      <description>Creative Cloud desktop app Update Service</description>
      <execute>0</execute>
      <action>
        <plugin>Services</plugin>
        <params>
          <name>AdobeUpdateService</name>
          <value>Disabled</value>
        </params>
      </action>
    </entry>
  </group>
  <group>
    <id>DropBox</id>
    <displayname>DropBox</displayname>
    <description>Configure DropBox items</description>
    <entry>
      <name>DropboxUpdateTaskMachineCore Task</name>
      <description>Keeps the Dropbox software updated.</description>
      <execute>1</execute>
      <action>
        <plugin>SchTasks</plugin>
        <params>
          <name>DropboxUpdateTaskMachineCore</name>
          <path>\</path>
          <value>Disabled</value>
        </params>
      </action>
    </entry>
    <entry>
      <name>DropboxUpdateTaskMachineUA Task</name>
      <description>Keeps the Dropbox software updated.</description>
      <execute>1</execute>
      <action>
        <plugin>SchTasks</plugin>
        <params>
          <name>DropboxUpdateTaskMachineUA</name>
          <path>\</path>
          <value>Disabled</value>
        </params>
      </action>
    </entry>
    <entry>
      <name>Dropbox Update Service (dbupdate)</name>
      <description>Keeps the Dropbox software updated.</description>
      <execute>1</execute>
      <action>
        <plugin>Services</plugin>
        <params>
          <name>dbupdate</name>
          <value>Disabled</value>
        </params>
      </action>
    </entry>
    <entry>
      <name>Dropbox Update Service (dbupdatem)</name>
      <description>Keeps the Dropbox software updated.</description>
      <execute>1</execute>
      <action>
        <plugin>Services</plugin>
        <params>
          <name>dbupdatem</name>
          <value>Disabled</value>
        </params>
      </action>
    </entry>
  </group>
  <group>
    <id>Google</id>
    <displayname>Google</displayname>
    <description>Configures Google items</description>
    <entry>
      <name>GoogleUpdateTaskMachineUA Task</name>
      <description>Google Automatic Update Service</description>
      <execute>1</execute>
      <action>
        <plugin>SchTasks</plugin>
        <params>
          <name>GoogleUpdateTaskMachineUA</name>
          <path>\</path>
          <value>Disabled</value>
        </params>
      </action>
    </entry>
    <entry>
      <name>GoogleUpdateTaskMachineCore Task</name>
      <description>Google Automatic Update Core</description>
      <execute>1</execute>
      <action>
        <plugin>SchTasks</plugin>
        <params>
          <name>GoogleUpdateTaskMachineCore</name>
          <path>\</path>
          <value>Disabled</value>
        </params>
      </action>
    </entry>
    <entry>
      <name>Google Update Service (gupdate)</name>
      <description>Google Update Service</description>
      <execute>1</execute>
      <action>
        <plugin>Services</plugin>
        <params>
          <name>gupdate</name>
          <value>Disabled</value>
        </params>
      </action>
    </entry>
    <entry>
      <name>Google Update Service (gupdatem)</name>
      <description>Google Update Service</description>
      <execute>1</execute>
      <action>
        <plugin>Services</plugin>
        <params>
          <name>gupdatem</name>
          <value>Disabled</value>
        </params>
      </action>
    </entry>
    <entry>
      <name>Google Chome Elevation Service (GoogleChromeElevationService)</name>
      <description>Currently the elevation service is only installed for Google Chrome builds. The Primary use case at the moment for the service has to do with the Chrome recovery component. The recovery component is registered only for Google Chrome builds. It repairs Chrome Updater (Google Update) when the algorithm detects that Chrome is not being updated. Since Chrome could be installed per-system or per-user, an elevation service is needed to repair code in the per-system install case.</description>
      <execute>1</execute>
      <action>
        <plugin>Services</plugin>
        <params>
          <name>GoogleChromeElevationService</name>
          <value>Disabled</value>
        </params>
      </action>
    </entry>
  </group>
  <group>
    <id>Citrix</id>
    <displayname>Citrix</displayname>
    <description>XenServer Management Agent Automatic Update Service</description>
    <entry>
      <name>Citrix Management Agent Auto-Updater Task</name>
      <description>Citrix (Hypervisor) Management Agent Auto-Updater</description>
      <execute>1</execute>
      <action>
        <plugin>SchTasks</plugin>
        <params>
          <name>Citrix Management Agent Auto-Updater</name>
          <path>\</path>
          <value>Disabled</value>
        </params>
      </action>
    </entry>
    <entry>
      <name>Citrix Personal vDisk Service (CitrixPvD)</name>
      <description>Citrix Personal vDisk Service</description>
      <execute>0</execute>
      <action>
        <plugin>Services</plugin>
        <params>
          <name>CitrixPvD</name>
          <value>Disabled</value>
        </params>
      </action>
    </entry>
    <entry>
      <name>Citrix Profile Manager Service (ctxProfile)</name>
      <description>Citrix Profile Manager Service
NOTE: the Desktop Ready Event logged by Citrix Profile Management (EventID 1000) is required for the Director to measure Login duration.</description>
      <execute>0</execute>
      <action>
        <plugin>Services</plugin>
        <params>
          <name>ctxProfile</name>
          <value>Disabled</value>
        </params>
      </action>
    </entry>
  </group>
  <group>
    <id>Microsoft</id>
    <displayname>Microsoft</displayname>
    <description>Configure Microsoft items</description>
    <entry>
      <name>Configuration Manager Idle Detection Task</name>
      <description>Configuration Manager Idle Detection</description>
      <execute>1</execute>
      <action>
        <plugin>SchTasks</plugin>
        <params>
          <name>Configuration Manager Idle Detection</name>
          <path>\Microsoft\Configuration Manager\</path>
          <value>Disabled</value>
        </params>
      </action>
    </entry>
    <entry>
      <name>Configuration Manager Maintenance Task</name>
      <description>Configuration Manager Maintenance</description>
      <execute>1</execute>
      <action>
        <plugin>SchTasks</plugin>
        <params>
          <name>Configuration Manager Maintenance</name>
          <path>\microsoft\Configuration Manager\</path>
          <value>Disabled</value>
        </params>
      </action>
    </entry>
    <entry>
      <name>OneDrive Per-Machine Standalone Update Task</name>
      <description>OneDrive Per-Machine Standalone Update Task</description>
      <execute>1</execute>
      <action>
        <plugin>SchTasks</plugin>
        <params>
          <name>OneDrive Per-Machine Standalone Update Task</name>
          <path>\</path>
          <value>Disabled</value>
        </params>
      </action>
    </entry>
    <entry>
      <name>System Center SMS Agent Host Service (CCMExec)</name>
      <description>System Center SMS Agent Host Service</description>
      <execute>1</execute>
      <action>
        <plugin>Services</plugin>
        <params>
          <name>CCMExec</name>
          <value>Disabled</value>
        </params>
      </action>
    </entry>
    <entry>
      <name>Microsoft Edge Update Service (edgeupdate)</name>
      <description>Keeps your Microsoft software up to date. If this service is disabled or stopped, your Microsoft software will not be kept up to date, meaning security vulnerabilities that may arise cannot be fixed and features may not work. This service uninstalls itself when there is no Microsoft software using it.</description>
      <execute>1</execute>
      <action>
        <plugin>Services</plugin>
        <params>
          <name>edgeupdate</name>
          <value>Disabled</value>
        </params>
      </action>
    </entry>
    <entry>
      <name>Microsoft Edge Update Service (edgeupdatem)</name>
      <description>Keeps your Microsoft software up to date. If this service is disabled or stopped, your Microsoft software will not be kept up to date, meaning security vulnerabilities that may arise cannot be fixed and features may not work. This service uninstalls itself when there is no Microsoft software using it.</description>
      <execute>1</execute>
      <action>
        <plugin>Services</plugin>
        <params>
          <name>edgeupdatem</name>
          <value>Disabled</value>
        </params>
      </action>
    </entry>
    <entry>
      <name>MicrosoftEdgeUpdateTaskMachineCore Task</name>
      <description>Keeps your Microsoft software up to date. If this task is disabled or stopped, your Microsoft software will not be kept up to date, meaning security vulnerabilities that may arise cannot be fixed and features may not work. This task uninstalls itself when there is no Microsoft software using it.</description>
      <execute>1</execute>
      <action>
        <plugin>SchTasks</plugin>
        <params>
          <name>MicrosoftEdgeUpdateTaskMachineCore</name>
          <path>\</path>
          <value>Disabled</value>
        </params>
      </action>
    </entry>
    <entry>
      <name>MicrosoftEdgeUpdateTaskMachineUA Task</name>
      <description>Keeps your Microsoft software up to date. If this task is disabled or stopped, your Microsoft software will not be kept up to date, meaning security vulnerabilities that may arise cannot be fixed and features may not work. This task uninstalls itself when there is no Microsoft software using it.</description>
      <execute>1</execute>
      <action>
        <plugin>SchTasks</plugin>
        <params>
          <name>MicrosoftEdgeUpdateTaskMachineUA</name>
          <path>\</path>
          <value>Disabled</value>
        </params>
      </action>
    </entry>
    <entry>
      <name>Office ClickToRun Service Monitor</name>
      <description>This task monitors the state of your Microsoft Office ClickToRunSvc and sends crash and error logs to Microsoft.</description>
      <execute>1</execute>
      <action>
        <plugin>SchTasks</plugin>
        <params>
          <name>Office ClickToRun Service Monitor</name>
          <path>\Microsoft\Office\</path>
          <value>Disabled</value>
        </params>
      </action>
    </entry>
    <entry>
      <name>Office Automatic Updates 2.0</name>
      <description>This task ensures that your Microsoft Office installation can check for updates.</description>
      <execute>1</execute>
      <action>
        <plugin>SchTasks</plugin>
        <params>
          <name>Office Automatic Updates 2.0</name>
          <path>\Microsoft\Office\</path>
          <value>Disabled</value>
        </params>
      </action>
    </entry>
    <entry>
      <name>Office Feature Updates</name>
      <description>This task ensures that your Microsoft Office installation can check for feature updates.</description>
      <execute>1</execute>
      <action>
        <plugin>SchTasks</plugin>
        <params>
          <name>Office Feature Updates</name>
          <path>\Microsoft\Office\</path>
          <value>Disabled</value>
        </params>
      </action>
    </entry>
    <entry>
      <name>Office Feature Updates Logon</name>
      <description>This task ensures that your Microsoft Office installation can check for feature updates.</description>
      <execute>1</execute>
      <action>
        <plugin>SchTasks</plugin>
        <params>
          <name>Office Feature Updates Logon</name>
          <path>\Microsoft\Office\</path>
          <value>Disabled</value>
        </params>
      </action>
    </entry>
    <entry>
      <name>OfficeTelemetryAgentFallBack2016</name>
      <description>This task initiates the background task for Office Telemetry Agent, which scans and uploads usage and error information for Office solutions.</description>
      <execute>1</execute>
      <action>
        <plugin>SchTasks</plugin>
        <params>
          <name>OfficeTelemetryAgentFallBack2016</name>
          <path>\Microsoft\Office\</path>
          <value>Disabled</value>
        </params>
      </action>
    </entry>
    <entry>
      <name>OfficeTelemetryAgentLogOn2016</name>
      <description>OfficeTelemetryAgentFallBack2016</description>
      <execute>1</execute>
      <action>
        <plugin>SchTasks</plugin>
        <params>
          <name>OfficeTelemetryAgentLogOn2016</name>
          <path>\Microsoft\Office\</path>
          <value>Disabled</value>
        </params>
      </action>
    </entry>
  </group>
  <group>
    <id>Mozilla</id>
    <displayname>Mozilla</displayname>
    <description>Configure Mozilla items</description>
    <entry>
      <name>Mozilla Maintenance Service (MozillaMaintenance)</name>
      <description>Mozilla Maintenance Service</description>
      <execute>1</execute>
      <action>
        <plugin>Services</plugin>
        <params>
          <name>MozillaMaintenance</name>
          <value>Disabled</value>
        </params>
      </action>
    </entry>
  </group>
  <group>
    <id>Ivanti</id>
    <displayname>Ivanti</displayname>
    <description>Configure Ivanti items</description>
    <entry>
      <name>Ivanti Automation Console Service (RESWCS)</name>
      <description>Ivanti Automation Console Service</description>
      <execute>1</execute>
      <action>
        <plugin>Services</plugin>
        <params>
          <name>RESWCS</name>
          <value>Disabled</value>
        </params>
      </action>
    </entry>
  </group>
  <group>
    <id>Oracle</id>
    <displayname>Oracle</displayname>
    <description>Oracle Java settings</description>
    <entry>
      <name>Delete SunJavaUpdateSched (x64)</name>
      <description>Delete Java update check autostart</description>
      <execute>1</execute>
      <action>
        <plugin>Registry</plugin>
        <params>
          <name>SunJavaUpdateSched</name>
          <path>HKLM\SOFTWARE\Wow6432Node\Microsoft\Windows\CurrentVersion\Run</path>
          <value>CTXOE_DeleteValue</value>
          <valuetype>String</valuetype>
        </params>
      </action>
    </entry>
    <entry>
      <name>Delete SunJavaUpdateSched (x86)</name>
      <description>Delete Java update check autostart</description>
      <execute>1</execute>
      <action>
        <plugin>Registry</plugin>
        <params>
          <name>SunJavaUpdateSched</name>
          <path>HKLM\SOFTWARE\Microsoft\Windows\CurrentVersion\Run</path>
          <value>CTXOE_DeleteValue</value>
          <valuetype>String</valuetype>
        </params>
      </action>
    </entry>
    <entry>
      <name>Disable Download Notify (x64)</name>
      <description>Disable Download Notify</description>
      <execute>1</execute>
      <action>
        <plugin>Registry</plugin>
        <params>
          <name>NotifyDownload</name>
          <path>HKLM\SOFTWARE\Wow6432Node\JavaSoft\Java Update\Policy</path>
          <value>0</value>
          <valuetype>Dword</valuetype>
        </params>
      </action>
    </entry>
    <entry>
      <name>Disable Download Notify (x86)</name>
      <description>Disable Download Notify</description>
      <execute>1</execute>
      <action>
        <plugin>Registry</plugin>
        <params>
          <name>NotifyDownload</name>
          <path>HKLM\SOFTWARE\JavaSoft\Java Update\Policy</path>
          <value>0</value>
          <valuetype>Dword</valuetype>
        </params>
      </action>
    </entry>
    <entry>
      <name>Disable Java auto update check (x64)</name>
      <description>Disable Java auto update check</description>
      <execute>1</execute>
      <action>
        <plugin>Registry</plugin>
        <params>
          <name>EnableAutoUpdateCheck</name>
          <path>HKLM\SOFTWARE\Wow6432Node\JavaSoft\Java Update\Policy</path>
          <value>0</value>
          <valuetype>Dword</valuetype>
        </params>
      </action>
    </entry>
    <entry>
      <name>Disable Java auto update check (x86)</name>
      <description>Disable Java auto update check</description>
      <execute>1</execute>
      <action>
        <plugin>Registry</plugin>
        <params>
          <name>EnableAutoUpdateCheck</name>
          <path>HKLM\SOFTWARE\JavaSoft\Java Update\Policy</path>
          <value>0</value>
          <valuetype>Dword</valuetype>
        </params>
      </action>
    </entry>
    <entry>
      <name>Disable Java update (x64)</name>
      <description>Disable Java update</description>
      <execute>1</execute>
      <action>
        <plugin>Registry</plugin>
        <params>
          <name>EnableJavaUpdate</name>
          <path>HKLM\SOFTWARE\Wow6432Node\JavaSoft\Java Update\Policy</path>
          <value>0</value>
          <valuetype>Dword</valuetype>
        </params>
      </action>
    </entry>
    <entry>
      <name>Disable Java update (x86)</name>
      <description>Disable Java update</description>
      <execute>1</execute>
      <action>
        <plugin>Registry</plugin>
        <params>
          <name>EnableJavaUpdate</name>
          <path>HKLM\SOFTWARE\JavaSoft\Java Update\Policy</path>
          <value>0</value>
          <valuetype>Dword</valuetype>
        </params>
      </action>
    </entry>
  </group>
</root>